ume_application_model/__init__.py
ume_application_model/ume_application_model.py
ume_application_model-0.1.0.dist-info/LICENSE
ume_application_model-0.1.0.dist-info/METADATA
ume_application_model-0.1.0.dist-info/WHEEL
ume_application_model-0.1.0.dist-info/RECORD
