Metadata-Version: 2.1
Name: ume_application_model
Version: 0.1.0
Summary: Generate application score for a new customer.
License: Proprietary
Author: Wesllen Sousa Lima
Requires-Python: >=3.9,<4.0
Classifier: License :: Other/Proprietary License
Classifier: Programming Language :: Python :: 3
Classifier: Programming Language :: Python :: 3.9
Classifier: Programming Language :: Python :: 3.10
Classifier: Programming Language :: Python :: 3.11
Classifier: Programming Language :: Python :: 3.12
